iWAN_Request/__init__.py
iWAN_Request/iWAN_Request.py
iWAN_Request-0.0.4.dist-info/METADATA
iWAN_Request-0.0.4.dist-info/WHEEL
iWAN_Request-0.0.4.dist-info/top_level.txt
iWAN_Request-0.0.4.dist-info/RECORD
