Metadata-Version: 2.1
Name: iWAN-Request
Version: 0.0.4
Summary: simple tool
Home-page: https://github.com/Nevquit/iWAN_Request
Author: vSir
Author-email: weiguo341@gmail.com
Classifier: Programming Language :: Python :: 3
Classifier: License :: OSI Approved :: MIT License
Classifier: Operating System :: OS Independent
